[
    {
        "key": "datr",
        "value": "s0kkaT_v7eQZ5y2qVVQr3mLC",
        "domain": "facebook.com",
        "path": "/",
        "hostOnly": false,
        "creation": "2025-11-24T12:25:06.317Z",
        "lastAccessed": "2025-11-24T12:25:06.318Z"
    },
    {
        "key": "sb",
        "value": "s0kkaR2IYER-i7G-WYYX-DwF",
        "domain": "facebook.com",
        "path": "/",
        "hostOnly": false,
        "creation": "2025-11-24T12:25:06.318Z",
        "lastAccessed": "2025-11-24T12:25:06.318Z"
    },
    {
        "key": "m_pixel_ratio",
        "value": "1.8000000715255737",
        "domain": "facebook.com",
        "path": "/",
        "hostOnly": false,
        "creation": "2025-11-24T12:25:06.318Z",
        "lastAccessed": "2025-11-24T12:25:06.318Z"
    },
    {
        "key": "wd",
        "value": "400x889",
        "domain": "facebook.com",
        "path": "/",
        "hostOnly": false,
        "creation": "2025-11-24T12:25:06.318Z",
        "lastAccessed": "2025-11-24T12:25:06.318Z"
    },
    {
        "key": "c_user",
        "value": "61580598123183",
        "domain": "facebook.com",
        "path": "/",
        "hostOnly": false,
        "creation": "2025-11-24T12:25:06.318Z",
        "lastAccessed": "2025-11-24T12:25:06.318Z"
    },
    {
        "key": "xs",
        "value": "24%3A-bqYj_Cf7rp96w%3A2%3A1763985923%3A-1%3A-1",
        "domain": "facebook.com",
        "path": "/",
        "hostOnly": false,
        "creation": "2025-11-24T12:25:06.318Z",
        "lastAccessed": "2025-11-24T12:25:06.318Z"
    },
    {
        "key": "locale",
        "value": "en_US",
        "domain": "facebook.com",
        "path": "/",
        "hostOnly": false,
        "creation": "2025-11-24T12:25:06.318Z",
        "lastAccessed": "2025-11-24T12:25:06.318Z"
    },
    {
        "key": "pas",
        "value": "61580598123183%3AuPdSjh0Fzd",
        "domain": "facebook.com",
        "path": "/",
        "hostOnly": false,
        "creation": "2025-11-24T12:25:06.318Z",
        "lastAccessed": "2025-11-24T12:25:06.318Z"
    },
    {
        "key": "vpd",
        "value": "v1%3B789x400x1.8000000715255737",
        "domain": "facebook.com",
        "path": "/",
        "hostOnly": false,
        "creation": "2025-11-24T12:25:06.318Z",
        "lastAccessed": "2025-11-24T12:25:06.318Z"
    },
    {
        "key": "fr",
        "value": "0zzLl20dcpaLzZtNX.AWcmmBTw14JrCBYT-RdQkyGMTdSsQ-CXd_1eTFKQQMHjU9jIJP8.BpJEmz..AAA.0.0.BpJE3E.AWdlJhqIPy-SrEadn4valCBwAtE",
        "domain": "facebook.com",
        "path": "/",
        "hostOnly": false,
        "creation": "2025-11-24T12:25:06.318Z",
        "lastAccessed": "2025-11-24T12:25:06.318Z"
    },
    {
        "key": "fbl_st",
        "value": "100427251%3BT%3A29399781",
        "domain": "facebook.com",
        "path": "/",
        "hostOnly": false,
        "creation": "2025-11-24T12:25:06.318Z",
        "lastAccessed": "2025-11-24T12:25:06.318Z"
    },
    {
        "key": "wl_cbv",
        "value": "v2%3Bclient_version%3A2994%3Btimestamp%3A1763986884",
        "domain": "facebook.com",
        "path": "/",
        "hostOnly": false,
        "creation": "2025-11-24T12:25:06.318Z",
        "lastAccessed": "2025-11-24T12:25:06.318Z"
    }
]
